coloreflection/__init__.py
coloreflection/main.py
coloreflection-0.1.0.dist-info/LICENSE
coloreflection-0.1.0.dist-info/METADATA
coloreflection-0.1.0.dist-info/WHEEL
coloreflection-0.1.0.dist-info/RECORD
