Metadata-Version: 2.1
Name: coloreflection
Version: 0.1.0
Summary: Module for using colors for the terminal, based on reflection
Home-page: https://github.com/Addefan/coloreflection
License: GPL-3.0-or-later
Keywords: colorist,terminal
Author: Vitaly Zorin
Author-email: addefan@mail.ru
Requires-Python: >=3.0,<4.0
Classifier: License :: OSI Approved :: GNU General Public License v3 or later (GPLv3+)
Classifier: Programming Language :: Python :: 3
Classifier: Programming Language :: Python :: 3.4
Classifier: Programming Language :: Python :: 3.5
Classifier: Programming Language :: Python :: 3.6
Classifier: Programming Language :: Python :: 3.7
Classifier: Programming Language :: Python :: 3.8
Classifier: Programming Language :: Python :: 3.9
Classifier: Programming Language :: Python :: 3.10
Classifier: Programming Language :: Python :: 3.11
Project-URL: Repository, https://github.com/Addefan/coloreflection
